agentic_dev_boilerplate/__init__.py
agentic_dev_boilerplate/generate_boilerplate.py
agentic_dev_boilerplate/git_setup.py
agentic_dev_boilerplate/multi_agent_solver.py
agentic_dev_boilerplate/setup_uv.py
agentic_dev_boilerplate/tmp_manager.py
agentic_dev_boilerplate/tmp_manager.py.backup
agentic_dev_boilerplate/templates/README.md.j2
agentic_dev_boilerplate/templates/agent_ai_engineer_instructions.md.j2
agentic_dev_boilerplate/templates/agent_base_instructions.md.j2
agentic_dev_boilerplate/templates/agent_debugger_instructions.md.j2
agentic_dev_boilerplate/templates/agent_deployer_instructions.md.j2
agentic_dev_boilerplate/templates/agent_devops_specialist_instructions.md.j2
agentic_dev_boilerplate/templates/agent_orchestrator_instructions.md.j2
agentic_dev_boilerplate/templates/agent_planner_instructions.md.j2
agentic_dev_boilerplate/templates/agent_software_engineer_instructions.md.j2
agentic_dev_boilerplate/templates/agent_systems_engineer_instructions.md.j2
agentic_dev_boilerplate/templates/agent_tester_instructions.md.j2
agentic_dev_boilerplate/templates/pyproject.toml.j2
agentic_dev_boilerplate/templates/requirements.txt.j2
agentic_dev_boilerplate/templates/script_git_setup.py.j2
agentic_dev_boilerplate/templates/script_multi_agent_solver.py.j2
agentic_dev_boilerplate/templates/script_setup_uv.py.j2
agentic_dev_boilerplate/templates/workflow_agent_coordination.yml.j2
agentic_dev_boilerplate/templates/workflow_ci_cd.yml.j2
agentic_dev_boilerplate/templates/workflow_ci_cd.yml.j2.backup
agentic_dev_boilerplate/templates/workflow_pr_automation.yml.j2
agentic_dev_boilerplate-1.1.2.dist-info/METADATA
agentic_dev_boilerplate-1.1.2.dist-info/WHEEL
agentic_dev_boilerplate-1.1.2.dist-info/entry_points.txt
agentic_dev_boilerplate-1.1.2.dist-info/RECORD
