Metadata-Version: 2.4
Name: agentic-dev-boilerplate
Version: 1.1.2
Summary: Templatized repository for generating agentic development workflows and automations
Project-URL: Homepage, https://github.com/tzervas/agentic-dev-boilerplate
Project-URL: Repository, https://github.com/tzervas/agentic-dev-boilerplate
Project-URL: Changelog, https://github.com/tzervas/agentic-dev-boilerplate/blob/main/CHANGELOG.md
Project-URL: Contributing, https://github.com/tzervas/agentic-dev-boilerplate/blob/main/CONTRIBUTING.md
Author-email: Your Name <your.email@example.com>
Maintainer-email: Your Name <your.email@example.com>
Keywords: python
Classifier: Development Status :: 3 - Alpha
Classifier: Intended Audience :: Developers
Classifier: Programming Language :: Python :: 3.11
Classifier: Topic :: Software Development
Requires-Python: >=3.11
Requires-Dist: black==25.12.0
Requires-Dist: click==8.3.1
Requires-Dist: flake8==7.3.0
Requires-Dist: isort==7.0.0
Requires-Dist: jinja2==3.1.6
Requires-Dist: mypy==1.19.1
Requires-Dist: pytest-cov==7.0.0
Requires-Dist: pytest==9.0.2
Requires-Dist: pyyaml==6.0.3
Provides-Extra: dev
Requires-Dist: black; extra == 'dev'
Requires-Dist: flake8; extra == 'dev'
Requires-Dist: isort; extra == 'dev'
Requires-Dist: mypy; extra == 'dev'
Requires-Dist: pytest; extra == 'dev'
Requires-Dist: pytest-cov; extra == 'dev'
Provides-Extra: docs
Requires-Dist: sphinx-rtd-theme==3.0.2; extra == 'docs'
Requires-Dist: sphinx==7.4.7; extra == 'docs'
